arrendatools_plantillas/__init__.py
arrendatools_plantillas/plantilla.py
arrendatools_plantillas/filters/__init__.py
arrendatools_plantillas/filters/formato_fecha.py
arrendatools_plantillas/filters/numero_a_palabras.py
arrendatools_plantillas-2.0.0.dist-info/LICENSE
arrendatools_plantillas-2.0.0.dist-info/METADATA
arrendatools_plantillas-2.0.0.dist-info/WHEEL
arrendatools_plantillas-2.0.0.dist-info/top_level.txt
arrendatools_plantillas-2.0.0.dist-info/RECORD
